{"v":"5.6.9","fr":30,"ip":0,"op":130,"w":1920,"h":1080,"nm":"prontinho","ddd":0,"assets":[{"id":"image_0","w":1024,"h":720,"u":"images/","p":"globo.png","e":0},{"id":"comp_0","layers":[{"ddd":0,"ind":1,"ty":5,"nm":"fique em casa","sr":1,"ks":{"o":{"a":0,"k":100,"ix":11},"r":{"a":0,"k":0,"ix":10},"p":{"a":0,"k":[960,472,0],"ix":2},"a":{"a":0,"k":[0,0,0],"ix":1},"s":{"a":0,"k":[100,100,100],"ix":6}},"ao":0,"sy":[{"c":{"a":0,"k":[0,0,0,1],"ix":2},"o":{"a":0,"k":75,"ix":3},"a":{"a":0,"k":120,"ix":5},"s":{"a":0,"k":5,"ix":8},"d":{"a":0,"k":5,"ix":6},"ch":{"a":0,"k":0,"ix":7},"bm":{"a":0,"k":5,"ix":1},"no":{"a":0,"k":0,"ix":9},"lc":{"a":0,"k":1,"ix":10},"ty":1,"nm":"Sombra projetada"},{"c":{"a":0,"k":[0,0,0,1],"ix":2},"o":{"a":0,"k":75,"ix":3},"a":{"a":0,"k":120,"ix":5},"s":{"a":0,"k":5,"ix":8},"d":{"a":0,"k":5,"ix":6},"ch":{"a":0,"k":0,"ix":7},"bm":{"a":0,"k":5,"ix":1},"no":{"a":0,"k":0,"ix":9},"ty":2,"nm":"Sombra interna"},{"c":{"a":0,"k":[1,1,0.745098039216,1],"ix":5},"o":{"a":0,"k":75,"ix":2},"s":{"a":0,"k":5,"ix":10},"r":{"a":0,"k":50,"ix":11},"ch":{"a":0,"k":0,"ix":9},"bm":{"a":0,"k":11,"ix":1},"no":{"a":0,"k":0,"ix":3},"j":{"a":0,"k":0,"ix":12},"ty":3,"nm":"Brilho externo"},{"c":{"a":0,"k":[1,1,0.745098039216,1],"ix":5},"o":{"a":0,"k":75,"ix":2},"s":{"a":0,"k":5,"ix":11},"r":{"a":0,"k":50,"ix":12},"sr":{"a":0,"k":1,"ix":9},"ch":{"a":0,"k":0,"ix":10},"bm":{"a":0,"k":11,"ix":1},"no":{"a":0,"k":0,"ix":3},"j":{"a":0,"k":0,"ix":13},"ty":4,"nm":"Brilho interno"},{"c":{"a":0,"k":[1,0,0,1],"ix":2},"s":{"a":0,"k":3,"ix":3},"ty":0,"nm":"Traçado"}],"t":{"d":{"k":[{"s":{"s":150,"f":"BebasNeue-Regular","t":"fique em casa","j":2,"tr":50,"lh":180,"ls":0,"fc":[0,0,0]},"t":0}]},"p":{},"m":{"g":1,"a":{"a":0,"k":[0,0],"ix":2}},"a":[]},"ip":0,"op":300,"st":0,"bm":0},{"ddd":0,"ind":2,"ty":5,"nm":"com","sr":1,"ks":{"o":{"a":0,"k":100,"ix":11},"r":{"a":0,"k":0,"ix":10},"p":{"a":0,"k":[960,550,0],"ix":2},"a":{"a":0,"k":[0,0,0],"ix":1},"s":{"a":0,"k":[100,100,100],"ix":6}},"ao":0,"sy":[{"c":{"a":0,"k":[0,0,0,1],"ix":2},"o":{"a":0,"k":75,"ix":3},"a":{"a":0,"k":120,"ix":5},"s":{"a":0,"k":5,"ix":8},"d":{"a":0,"k":5,"ix":6},"ch":{"a":0,"k":0,"ix":7},"bm":{"a":0,"k":5,"ix":1},"no":{"a":0,"k":0,"ix":9},"lc":{"a":0,"k":1,"ix":10},"ty":1,"nm":"Sombra projetada"},{"c":{"a":0,"k":[0,0,0,1],"ix":2},"o":{"a":0,"k":75,"ix":3},"a":{"a":0,"k":120,"ix":5},"s":{"a":0,"k":5,"ix":8},"d":{"a":0,"k":5,"ix":6},"ch":{"a":0,"k":0,"ix":7},"bm":{"a":0,"k":5,"ix":1},"no":{"a":0,"k":0,"ix":9},"ty":2,"nm":"Sombra interna"},{"c":{"a":0,"k":[1,1,0.745098039216,1],"ix":5},"o":{"a":0,"k":75,"ix":2},"s":{"a":0,"k":5,"ix":10},"r":{"a":0,"k":50,"ix":11},"ch":{"a":0,"k":0,"ix":9},"bm":{"a":0,"k":11,"ix":1},"no":{"a":0,"k":0,"ix":3},"j":{"a":0,"k":0,"ix":12},"ty":3,"nm":"Brilho externo"},{"c":{"a":0,"k":[1,1,0.745098039216,1],"ix":5},"o":{"a":0,"k":75,"ix":2},"s":{"a":0,"k":5,"ix":11},"r":{"a":0,"k":50,"ix":12},"sr":{"a":0,"k":1,"ix":9},"ch":{"a":0,"k":0,"ix":10},"bm":{"a":0,"k":11,"ix":1},"no":{"a":0,"k":0,"ix":3},"j":{"a":0,"k":0,"ix":13},"ty":4,"nm":"Brilho interno"},{"c":{"a":0,"k":[1,0,0,1],"ix":2},"s":{"a":0,"k":3,"ix":3},"ty":0,"nm":"Traçado"}],"t":{"d":{"k":[{"s":{"s":60,"f":"BebasNeue-Regular","t":"com","j":2,"tr":50,"lh":72,"ls":0,"fc":[0,0,0]},"t":0}]},"p":{},"m":{"g":1,"a":{"a":0,"k":[0,0],"ix":2}},"a":[]},"ip":0,"op":300,"st":0,"bm":0},{"ddd":0,"ind":3,"ty":5,"nm":"globo.com","cl":"com","sr":1,"ks":{"o":{"a":0,"k":100,"ix":11},"r":{"a":0,"k":0,"ix":10},"p":{"a":0,"k":[960,626,0],"ix":2},"a":{"a":0,"k":[-1.343,-32.379,0],"ix":1},"s":{"a":0,"k":[100,100,100],"ix":6}},"ao":0,"sy":[{"c":{"a":0,"k":[0,0,0,1],"ix":2},"o":{"a":0,"k":75,"ix":3},"a":{"a":0,"k":120,"ix":5},"s":{"a":0,"k":5,"ix":8},"d":{"a":0,"k":5,"ix":6},"ch":{"a":0,"k":0,"ix":7},"bm":{"a":0,"k":5,"ix":1},"no":{"a":0,"k":0,"ix":9},"lc":{"a":0,"k":1,"ix":10},"ty":1,"nm":"Sombra projetada"},{"c":{"a":0,"k":[0,0,0,1],"ix":2},"o":{"a":0,"k":75,"ix":3},"a":{"a":0,"k":120,"ix":5},"s":{"a":0,"k":5,"ix":8},"d":{"a":0,"k":5,"ix":6},"ch":{"a":0,"k":0,"ix":7},"bm":{"a":0,"k":5,"ix":1},"no":{"a":0,"k":0,"ix":9},"ty":2,"nm":"Sombra interna"},{"c":{"a":0,"k":[1,1,0.745098039216,1],"ix":5},"o":{"a":0,"k":75,"ix":2},"s":{"a":0,"k":5,"ix":10},"r":{"a":0,"k":50,"ix":11},"ch":{"a":0,"k":0,"ix":9},"bm":{"a":0,"k":11,"ix":1},"no":{"a":0,"k":0,"ix":3},"j":{"a":0,"k":0,"ix":12},"ty":3,"nm":"Brilho externo"},{"c":{"a":0,"k":[1,1,0.745098039216,1],"ix":5},"o":{"a":0,"k":75,"ix":2},"s":{"a":0,"k":5,"ix":11},"r":{"a":0,"k":50,"ix":12},"sr":{"a":0,"k":1,"ix":9},"ch":{"a":0,"k":0,"ix":10},"bm":{"a":0,"k":11,"ix":1},"no":{"a":0,"k":0,"ix":3},"j":{"a":0,"k":0,"ix":13},"ty":4,"nm":"Brilho interno"},{"c":{"a":0,"k":[1,0,0,1],"ix":2},"s":{"a":0,"k":3,"ix":3},"ty":0,"nm":"Traçado"}],"t":{"d":{"k":[{"s":{"s":125,"f":"ArialRoundedMTBold","t":"globo.com","j":2,"tr":50,"lh":150,"ls":0,"fc":[0.004,0.616,0.855]},"t":0}]},"p":{},"m":{"g":1,"a":{"a":0,"k":[0,0],"ix":2}},"a":[]},"ip":0,"op":300,"st":0,"bm":0}]}],"fonts":{"list":[{"fName":"ArialRoundedMTBold","fFamily":"Arial Rounded MT Bold","fStyle":"Regular","ascent":74.0203857421875},{"fName":"BebasNeue-Regular","fFamily":"Bebas Neue","fStyle":"Regular","ascent":69.9996948242188}]},"layers":[{"ddd":0,"ind":1,"ty":3,"nm":"Camada de ajuste 1","sr":1,"ks":{"o":{"a":0,"k":100,"ix":11},"r":{"a":0,"k":0,"ix":10},"p":{"a":0,"k":[960,540,0],"ix":2},"a":{"a":0,"k":[960,540,0],"ix":1},"s":{"a":0,"k":[100,100,100],"ix":6}},"ao":0,"ef":[{"ty":5,"nm":"CC Light Sweep","np":11,"mn":"CC Light Sweep","ix":1,"en":1,"ef":[{"ty":3,"nm":"Center","mn":"CC Light Sweep-0001","ix":1,"v":{"a":1,"k":[{"i":{"x":0.667,"y":1},"o":{"x":0.333,"y":0},"t":68,"s":[72,168],"to":[272.667,2],"ti":[-272.667,-2]},{"t":130,"s":[1708,180]}],"ix":1}},{"ty":0,"nm":"Direction","mn":"CC Light Sweep-0002","ix":2,"v":{"a":0,"k":-30,"ix":2}},{"ty":7,"nm":"Shape","mn":"CC Light Sweep-0003","ix":3,"v":{"a":0,"k":3,"ix":3}},{"ty":0,"nm":"Width","mn":"CC Light Sweep-0004","ix":4,"v":{"a":0,"k":50,"ix":4}},{"ty":0,"nm":"Sweep Intensity","mn":"CC Light Sweep-0005","ix":5,"v":{"a":0,"k":25,"ix":5}},{"ty":0,"nm":"Edge Intensity","mn":"CC Light Sweep-0006","ix":6,"v":{"a":0,"k":50,"ix":6}},{"ty":0,"nm":"Edge Thickness","mn":"CC Light Sweep-0007","ix":7,"v":{"a":0,"k":4,"ix":7}},{"ty":2,"nm":"Light Color","mn":"CC Light Sweep-0008","ix":8,"v":{"a":0,"k":[1,0.980392156863,0.941176470588,1],"ix":8}},{"ty":7,"nm":"Light Reception","mn":"CC Light Sweep-0009","ix":9,"v":{"a":0,"k":1,"ix":9}}]}],"sy":[{"c":{"a":0,"k":[0,0,0,1],"ix":2},"o":{"a":0,"k":75,"ix":3},"a":{"a":0,"k":120,"ix":5},"s":{"a":0,"k":5,"ix":8},"d":{"a":0,"k":5,"ix":6},"ch":{"a":0,"k":0,"ix":7},"bm":{"a":0,"k":5,"ix":1},"no":{"a":0,"k":0,"ix":9},"lc":{"a":0,"k":1,"ix":10},"ty":1,"nm":"Sombra projetada"},{"c":{"a":0,"k":[0,0,0,1],"ix":2},"o":{"a":0,"k":75,"ix":3},"a":{"a":0,"k":120,"ix":5},"s":{"a":0,"k":5,"ix":8},"d":{"a":0,"k":5,"ix":6},"ch":{"a":0,"k":0,"ix":7},"bm":{"a":0,"k":5,"ix":1},"no":{"a":0,"k":0,"ix":9},"ty":2,"nm":"Sombra interna"},{"c":{"a":0,"k":[1,1,0.745098039216,1],"ix":5},"o":{"a":0,"k":75,"ix":2},"s":{"a":0,"k":5,"ix":10},"r":{"a":0,"k":50,"ix":11},"ch":{"a":0,"k":0,"ix":9},"bm":{"a":0,"k":11,"ix":1},"no":{"a":0,"k":0,"ix":3},"j":{"a":0,"k":0,"ix":12},"ty":3,"nm":"Brilho externo"},{"c":{"a":0,"k":[1,1,0.745098039216,1],"ix":5},"o":{"a":0,"k":75,"ix":2},"s":{"a":0,"k":5,"ix":11},"r":{"a":0,"k":50,"ix":12},"sr":{"a":0,"k":1,"ix":9},"ch":{"a":0,"k":0,"ix":10},"bm":{"a":0,"k":11,"ix":1},"no":{"a":0,"k":0,"ix":3},"j":{"a":0,"k":0,"ix":13},"ty":4,"nm":"Brilho interno"},{"c":{"a":0,"k":[1,0,0,1],"ix":2},"s":{"a":0,"k":3,"ix":3},"ty":0,"nm":"Traçado"}],"ip":0,"op":300,"st":0,"bm":0},{"ddd":0,"ind":2,"ty":3,"nm":"guia","sr":1,"ks":{"o":{"a":0,"k":0,"ix":11},"r":{"a":0,"k":0,"ix":10},"p":{"a":1,"k":[{"i":{"x":0.167,"y":1},"o":{"x":0.604,"y":0},"t":37,"s":[960,540,0],"to":[-69.167,0,0],"ti":[69.167,0,0]},{"t":71,"s":[545,540,0]}],"ix":2},"a":{"a":0,"k":[0,0,0],"ix":1},"s":{"a":0,"k":[100,100,100],"ix":6}},"ao":0,"sy":[{"c":{"a":0,"k":[0,0,0,1],"ix":2},"o":{"a":0,"k":75,"ix":3},"a":{"a":0,"k":120,"ix":5},"s":{"a":0,"k":5,"ix":8},"d":{"a":0,"k":5,"ix":6},"ch":{"a":0,"k":0,"ix":7},"bm":{"a":0,"k":5,"ix":1},"no":{"a":0,"k":0,"ix":9},"lc":{"a":0,"k":1,"ix":10},"ty":1,"nm":"Sombra projetada"},{"c":{"a":0,"k":[0,0,0,1],"ix":2},"o":{"a":0,"k":75,"ix":3},"a":{"a":0,"k":120,"ix":5},"s":{"a":0,"k":5,"ix":8},"d":{"a":0,"k":5,"ix":6},"ch":{"a":0,"k":0,"ix":7},"bm":{"a":0,"k":5,"ix":1},"no":{"a":0,"k":0,"ix":9},"ty":2,"nm":"Sombra interna"},{"c":{"a":0,"k":[1,1,0.745098039216,1],"ix":5},"o":{"a":0,"k":75,"ix":2},"s":{"a":0,"k":5,"ix":10},"r":{"a":0,"k":50,"ix":11},"ch":{"a":0,"k":0,"ix":9},"bm":{"a":0,"k":11,"ix":1},"no":{"a":0,"k":0,"ix":3},"j":{"a":0,"k":0,"ix":12},"ty":3,"nm":"Brilho externo"},{"c":{"a":0,"k":[1,1,0.745098039216,1],"ix":5},"o":{"a":0,"k":75,"ix":2},"s":{"a":0,"k":5,"ix":11},"r":{"a":0,"k":50,"ix":12},"sr":{"a":0,"k":1,"ix":9},"ch":{"a":0,"k":0,"ix":10},"bm":{"a":0,"k":11,"ix":1},"no":{"a":0,"k":0,"ix":3},"j":{"a":0,"k":0,"ix":13},"ty":4,"nm":"Brilho interno"},{"c":{"a":0,"k":[1,0,0,1],"ix":2},"s":{"a":0,"k":3,"ix":3},"ty":0,"nm":"Traçado"}],"ip":0,"op":300,"st":0,"bm":0},{"ddd":0,"ind":3,"ty":4,"nm":"layer","td":1,"sr":1,"ks":{"o":{"a":0,"k":100,"ix":11},"r":{"a":0,"k":0,"ix":10},"p":{"a":0,"k":[960,540,0],"ix":2},"a":{"a":0,"k":[0,0,0],"ix":1},"s":{"a":0,"k":[100,100,100],"ix":6}},"ao":0,"sy":[{"c":{"a":0,"k":[0,0,0,1],"ix":2},"o":{"a":0,"k":75,"ix":3},"a":{"a":0,"k":120,"ix":5},"s":{"a":0,"k":5,"ix":8},"d":{"a":0,"k":5,"ix":6},"ch":{"a":0,"k":0,"ix":7},"bm":{"a":0,"k":5,"ix":1},"no":{"a":0,"k":0,"ix":9},"lc":{"a":0,"k":1,"ix":10},"ty":1,"nm":"Sombra projetada"},{"c":{"a":0,"k":[0,0,0,1],"ix":2},"o":{"a":0,"k":75,"ix":3},"a":{"a":0,"k":120,"ix":5},"s":{"a":0,"k":5,"ix":8},"d":{"a":0,"k":5,"ix":6},"ch":{"a":0,"k":0,"ix":7},"bm":{"a":0,"k":5,"ix":1},"no":{"a":0,"k":0,"ix":9},"ty":2,"nm":"Sombra interna"},{"c":{"a":0,"k":[1,1,0.745098039216,1],"ix":5},"o":{"a":0,"k":75,"ix":2},"s":{"a":0,"k":5,"ix":10},"r":{"a":0,"k":50,"ix":11},"ch":{"a":0,"k":0,"ix":9},"bm":{"a":0,"k":11,"ix":1},"no":{"a":0,"k":0,"ix":3},"j":{"a":0,"k":0,"ix":12},"ty":3,"nm":"Brilho externo"},{"c":{"a":0,"k":[1,1,0.745098039216,1],"ix":5},"o":{"a":0,"k":75,"ix":2},"s":{"a":0,"k":5,"ix":11},"r":{"a":0,"k":50,"ix":12},"sr":{"a":0,"k":1,"ix":9},"ch":{"a":0,"k":0,"ix":10},"bm":{"a":0,"k":11,"ix":1},"no":{"a":0,"k":0,"ix":3},"j":{"a":0,"k":0,"ix":13},"ty":4,"nm":"Brilho interno"},{"c":{"a":0,"k":[1,0,0,1],"ix":2},"s":{"a":0,"k":3,"ix":3},"ty":0,"nm":"Traçado"}],"shapes":[{"ty":"gr","it":[{"ind":0,"ty":"sh","ix":1,"ks":{"a":0,"k":{"i":[[0,0],[0,0],[0,0],[0,0],[0,0],[0,0],[0,0],[0,0],[0,0],[0,0],[0,0],[0,0],[0,0],[0,0],[0,0],[0,0],[0,0],[0,0],[0,0],[0,0],[0,0]],"o":[[0,0],[0,0],[0,0],[0,0],[0,0],[0,0],[0,0],[0,0],[0,0],[0,0],[0,0],[0,0],[0,0],[0,0],[0,0],[0,0],[0,0],[0,0],[0,0],[0,0],[0,0]],"v":[[-284,-382],[-1754,-376],[-1726,334],[-562,324],[-424,327],[-370,322],[-313,310],[-254,287],[-219,271],[-177,232],[-138,190],[-114,149],[-92,101],[-82,63],[-76,10],[-76,-35],[-82,-81],[-94,-123],[-115,-172],[-146,-220],[-199,-270]],"c":true},"ix":2},"nm":"Caminho 1","mn":"ADBE Vector Shape - Group","hd":false},{"ty":"fl","c":{"a":0,"k":[0.968626972273,0.968626972273,0.968626972273,1],"ix":4},"o":{"a":0,"k":100,"ix":5},"r":1,"bm":0,"nm":"Preenchimento 1","mn":"ADBE Vector Graphic - Fill","hd":false},{"ty":"tr","p":{"a":0,"k":[0,0],"ix":2},"a":{"a":0,"k":[0,0],"ix":1},"s":{"a":0,"k":[100,100],"ix":3},"r":{"a":0,"k":0,"ix":6},"o":{"a":0,"k":100,"ix":7},"sk":{"a":0,"k":0,"ix":4},"sa":{"a":0,"k":0,"ix":5},"nm":"Transformar"}],"nm":"Forma 1","np":3,"cix":2,"bm":0,"ix":1,"mn":"ADBE Vector Group","hd":false}],"ip":0,"op":300,"st":0,"bm":0},{"ddd":0,"ind":4,"ty":0,"nm":"textos","tt":2,"refId":"comp_0","sr":1,"ks":{"o":{"a":0,"k":100,"ix":11},"r":{"a":0,"k":0,"ix":10},"p":{"a":1,"k":[{"i":{"x":0.199,"y":1},"o":{"x":0.694,"y":0},"t":37,"s":[-448,540,0],"to":[289.5,0,0],"ti":[-289.5,0,0]},{"t":71,"s":[1289,540,0]}],"ix":2},"a":{"a":0,"k":[960,540,0],"ix":1},"s":{"a":0,"k":[100,100,100],"ix":6}},"ao":0,"sy":[{"c":{"a":0,"k":[0,0,0,1],"ix":2},"o":{"a":0,"k":75,"ix":3},"a":{"a":0,"k":120,"ix":5},"s":{"a":0,"k":5,"ix":8},"d":{"a":0,"k":5,"ix":6},"ch":{"a":0,"k":0,"ix":7},"bm":{"a":0,"k":5,"ix":1},"no":{"a":0,"k":0,"ix":9},"lc":{"a":0,"k":1,"ix":10},"ty":1,"nm":"Sombra projetada"},{"c":{"a":0,"k":[0,0,0,1],"ix":2},"o":{"a":0,"k":75,"ix":3},"a":{"a":0,"k":120,"ix":5},"s":{"a":0,"k":5,"ix":8},"d":{"a":0,"k":5,"ix":6},"ch":{"a":0,"k":0,"ix":7},"bm":{"a":0,"k":5,"ix":1},"no":{"a":0,"k":0,"ix":9},"ty":2,"nm":"Sombra interna"},{"c":{"a":0,"k":[1,1,0.745098039216,1],"ix":5},"o":{"a":0,"k":75,"ix":2},"s":{"a":0,"k":5,"ix":10},"r":{"a":0,"k":50,"ix":11},"ch":{"a":0,"k":0,"ix":9},"bm":{"a":0,"k":11,"ix":1},"no":{"a":0,"k":0,"ix":3},"j":{"a":0,"k":0,"ix":12},"ty":3,"nm":"Brilho externo"},{"c":{"a":0,"k":[1,1,0.745098039216,1],"ix":5},"o":{"a":0,"k":75,"ix":2},"s":{"a":0,"k":5,"ix":11},"r":{"a":0,"k":50,"ix":12},"sr":{"a":0,"k":1,"ix":9},"ch":{"a":0,"k":0,"ix":10},"bm":{"a":0,"k":11,"ix":1},"no":{"a":0,"k":0,"ix":3},"j":{"a":0,"k":0,"ix":13},"ty":4,"nm":"Brilho interno"},{"c":{"a":0,"k":[1,0,0,1],"ix":2},"s":{"a":0,"k":3,"ix":3},"ty":0,"nm":"Traçado"}],"w":1920,"h":1080,"ip":0,"op":300,"st":0,"bm":0},{"ddd":0,"ind":5,"ty":2,"nm":"globo.png","cl":"png","parent":2,"refId":"image_0","sr":1,"ks":{"o":{"a":0,"k":100,"ix":11},"r":{"a":0,"k":0,"ix":10},"p":{"a":0,"k":[-4,0,0],"ix":2},"a":{"a":0,"k":[512,360,0],"ix":1},"s":{"a":0,"k":[105.078,105.078,100],"ix":6}},"ao":0,"hasMask":true,"masksProperties":[{"inv":false,"mode":"n","pt":{"a":0,"k":{"i":[[-0.115,0.007],[13.056,-2.458],[24.618,-12.174],[23.869,-27.854],[1.024,-2.273],[0.246,-0.295],[2.286,-2.802],[1.508,-3.346],[0.247,-0.37],[0.23,-0.511],[0.244,-0.387],[1.271,-2.016],[1.185,-1.86],[2.326,-4.26],[4.836,-12.146],[-9.725,-57.167],[-1.106,-4.966],[-0.726,-2.999],[-0.679,-2.362],[-0.281,-1.254],[-0.163,-0.531],[-2.739,-6.993],[-5.983,-13.273],[-0.239,-0.407],[-1.281,-2.04],[-1.135,-1.778],[-10.977,-11.942],[-11.81,-9.638],[-1.738,-1.364],[-0.964,-0.674],[-0.852,-0.602],[-0.499,-0.225],[-0.37,-0.247],[-0.511,-0.23],[-0.353,-0.249],[-20.144,-8.633],[-3.116,-1.197],[-2.385,-0.841],[-4.69,-1.385],[-1.851,-0.411],[-1.577,-0.38],[-5.693,-1.042],[-33.296,5.741],[-4.775,1.092],[-14.7,6.291],[-14.696,9.545],[-8.433,7.075],[-1.821,1.534],[-1.778,1.628],[-6.363,6.849],[-13.416,31.304],[-1.016,2.371],[-1.436,4.002],[-0.825,2.372],[-2.073,7.967],[-0.547,2.27],[-0.593,2.816],[-0.505,2.756],[25.888,52.351],[28.082,26.655],[38.177,15.475],[51.24,-2.723]],"o":[[-16.366,1.054],[-30.773,5.794],[-35.941,17.773],[-2.124,2.479],[-0.124,0.274],[-3.055,3.666],[-2.878,3.528],[-0.146,0.324],[-0.307,0.46],[-0.151,0.334],[-1.27,2.012],[-1.124,1.783],[-2.76,4.331],[-5.68,10.399],[-18.536,46.557],[0.871,5.118],[0.67,3.008],[0.551,2.277],[0.354,1.233],[0.085,0.38],[2.545,8.301],[5.924,15.126],[0.156,0.346],[1.184,2.014],[1.085,1.728],[9.302,14.568],[11.107,12.084],[1.803,1.471],[0.865,0.679],[0.832,0.581],[0.441,0.311],[0.324,0.146],[0.46,0.307],[0.313,0.141],[17.74,12.487],[3.949,1.692],[2.669,1.026],[5.287,1.864],[2.964,0.875],[1.585,0.352],[5.314,1.281],[32.494,5.949],[5.253,-0.906],[18.489,-4.229],[17.828,-7.63],[9.822,-6.38],[1.705,-1.43],[1.91,-1.608],[6.691,-6.125],[22.187,-23.88],[1.17,-2.731],[1.548,-3.613],[0.81,-2.258],[2.894,-8.321],[0.605,-2.326],[0.699,-2.901],[0.637,-3.022],[13.656,-74.594],[-17.53,-35.45],[-25.846,-24.532],[-37.487,-15.196],[-0.629,0.033]],"v":[[507,35],[464,40],[384,68],[291,140],[286,147],[284,148],[276,159],[269,169],[267,170],[267,172],[265,173],[262,180],[258,185],[251,198],[235,231],[217,400],[221,415],[222,424],[225,431],[225,435],[227,438],[234,461],[255,505],[257,506],[260,513],[264,518],[294,557],[329,590],[334,595],[337,596],[339,599],[341,599],[342,601],[344,601],[345,603],[405,636],[415,640],[422,643],[438,647],[448,651],[453,651],[469,655],[578,656],[593,652],[645,636],[696,609],[724,588],[729,583],[735,579],[754,559],[810,474],[813,467],[817,457],[820,450],[826,427],[829,420],[830,411],[832,403],[804,207],[737,118],[642,57],[508,34]],"c":true},"ix":1},"o":{"a":0,"k":100,"ix":3},"x":{"a":0,"k":0,"ix":4},"nm":"Máscara 1"},{"inv":false,"mode":"n","pt":{"a":0,"k":{"i":[[0.665,-0.031],[29.446,-2.064],[13.707,-1.415],[6.165,-6.477],[1.031,-11.882],[0.416,-11.654],[-4.741,-60.633],[-5.254,-6.263],[-19.764,-1.646],[-16.869,-0.583],[-101.04,8.375],[-7.462,8.895],[-0.926,11.605],[2.057,57.701],[8.981,9.436],[15.116,1.561],[68.124,0],[27.997,-2.056],[-0.174,0.008]],"o":[[-30.174,1.404],[-11.846,0.83],[-11.265,1.163],[-5.762,6.055],[-1.016,11.706],[-2.349,65.896],[0.964,12.333],[7.553,9.002],[20.05,1.67],[106.209,3.673],[20.893,-1.732],[5.188,-6.184],[4.729,-59.299],[-0.83,-23.271],[-6.27,-6.588],[-62.758,-6.479],[-28.401,0],[-0.57,0.042],[-0.665,0.032]],"v":[[439,192],[358,195],[320,199],[287,208],[279,237],[277,272],[279,454],[286,485],[338,497],[398,501],[711,497],[764,485],[771,455],[773,273],[763,208],[730,199],[527,191],[442,191],[441,192]],"c":true},"ix":1},"o":{"a":0,"k":100,"ix":3},"x":{"a":0,"k":0,"ix":4},"nm":"Máscara 2"},{"inv":false,"mode":"n","pt":{"a":0,"k":{"i":[[0.153,-0.013],[12.451,-6.917],[1.389,-0.835],[10.407,-21.826],[0.217,-20.435],[-7.235,-14.47],[-5.684,-6.989],[-2.517,-2.544],[-1.697,-1.322],[-2.739,-2.08],[-0.962,-0.672],[-0.858,-0.588],[-1.811,-1.056],[-6.203,-2.539],[-22.013,1.937],[-14.117,9.365],[-0.94,0.623],[-0.94,0.623],[-5.114,6.253],[-2.17,3.105],[0.728,29.445],[7.697,16.144],[30.581,12.155],[23.514,-1.082]],"o":[[-20.272,1.664],[-1.518,0.843],[-22.28,13.401],[-7.22,15.142],[-0.246,23.123],[4.586,9.171],[2.391,2.939],[2.032,2.054],[2.897,2.257],[0.872,0.662],[0.83,0.58],[1.558,1.068],[6.308,3.68],[18.666,7.641],[22.25,-1.958],[1.662,-1.103],[1.662,-1.103],[7.485,-4.965],[2.428,-2.969],[13.368,-19.124],[-0.5,-20.215],[-13.962,-29.282],[-14.869,-5.91],[-0.85,0.039]],"v":[[516,221],[466,235],[461,237],[411,292],[398,345],[411,403],[427,427],[434,436],[441,441],[448,448],[451,449],[453,452],[459,455],[477,464],[539,473],[597,451],[601,448],[605,445],[622,428],[629,419],[652,343],[639,292],[573,230],[518,220]],"c":true},"ix":1},"o":{"a":0,"k":100,"ix":3},"x":{"a":0,"k":0,"ix":4},"nm":"Máscara 3"}],"ef":[{"ty":22,"nm":"Traçado","np":13,"mn":"ADBE Stroke","ix":1,"en":1,"ef":[{"ty":10,"nm":"Caminho","mn":"ADBE Stroke-0001","ix":1,"v":{"a":0,"k":1,"ix":1}},{"ty":7,"nm":"Todas as máscaras","mn":"ADBE Stroke-0010","ix":2,"v":{"a":0,"k":1,"ix":2}},{"ty":7,"nm":"Traçar sequencialmente","mn":"ADBE Stroke-0011","ix":3,"v":{"a":0,"k":0,"ix":3}},{"ty":2,"nm":"Cor","mn":"ADBE Stroke-0002","ix":4,"v":{"a":0,"k":[0.003921568859,0.615686297417,0.854901969433,1],"ix":4}},{"ty":0,"nm":"Tamanho do pincel","mn":"ADBE Stroke-0003","ix":5,"v":{"a":1,"k":[{"i":{"x":[0.667],"y":[1]},"o":{"x":[0.333],"y":[0]},"t":57,"s":[3.5]},{"i":{"x":[0.667],"y":[1]},"o":{"x":[0.333],"y":[0]},"t":63,"s":[9]},{"t":68,"s":[3.5]}],"ix":5}},{"ty":0,"nm":"Dureza do pincel","mn":"ADBE Stroke-0004","ix":6,"v":{"a":0,"k":0.75,"ix":6}},{"ty":0,"nm":"Opacidade","mn":"ADBE Stroke-0005","ix":7,"v":{"a":0,"k":1,"ix":7}},{"ty":0,"nm":"Início","mn":"ADBE Stroke-0008","ix":8,"v":{"a":0,"k":0,"ix":8}},{"ty":0,"nm":"Fim","mn":"ADBE Stroke-0009","ix":9,"v":{"a":1,"k":[{"i":{"x":[0],"y":[1]},"o":{"x":[0.333],"y":[0]},"t":0,"s":[0]},{"t":60,"s":[100]}],"ix":9}},{"ty":7,"nm":"Espaçamento","mn":"ADBE Stroke-0006","ix":10,"v":{"a":0,"k":15,"ix":10}},{"ty":7,"nm":"Estilo de pintura","mn":"ADBE Stroke-0007","ix":11,"v":{"a":0,"k":2,"ix":11}}]}],"sy":[{"c":{"a":0,"k":[0,0,0,1],"ix":2},"o":{"a":0,"k":75,"ix":3},"a":{"a":0,"k":120,"ix":5},"s":{"a":0,"k":5,"ix":8},"d":{"a":0,"k":5,"ix":6},"ch":{"a":0,"k":0,"ix":7},"bm":{"a":0,"k":5,"ix":1},"no":{"a":0,"k":0,"ix":9},"lc":{"a":0,"k":1,"ix":10},"ty":1,"nm":"Sombra projetada"},{"c":{"a":0,"k":[0,0,0,1],"ix":2},"o":{"a":0,"k":75,"ix":3},"a":{"a":0,"k":120,"ix":5},"s":{"a":0,"k":5,"ix":8},"d":{"a":0,"k":5,"ix":6},"ch":{"a":0,"k":0,"ix":7},"bm":{"a":0,"k":5,"ix":1},"no":{"a":0,"k":0,"ix":9},"ty":2,"nm":"Sombra interna"},{"c":{"a":0,"k":[1,1,0.745098039216,1],"ix":5},"o":{"a":0,"k":75,"ix":2},"s":{"a":0,"k":5,"ix":10},"r":{"a":0,"k":50,"ix":11},"ch":{"a":0,"k":0,"ix":9},"bm":{"a":0,"k":11,"ix":1},"no":{"a":0,"k":0,"ix":3},"j":{"a":0,"k":0,"ix":12},"ty":3,"nm":"Brilho externo"},{"c":{"a":0,"k":[1,1,0.745098039216,1],"ix":5},"o":{"a":0,"k":75,"ix":2},"s":{"a":0,"k":5,"ix":11},"r":{"a":0,"k":50,"ix":12},"sr":{"a":0,"k":1,"ix":9},"ch":{"a":0,"k":0,"ix":10},"bm":{"a":0,"k":11,"ix":1},"no":{"a":0,"k":0,"ix":3},"j":{"a":0,"k":0,"ix":13},"ty":4,"nm":"Brilho interno"},{"c":{"a":0,"k":[1,0,0,1],"ix":2},"s":{"a":0,"k":3,"ix":3},"ty":0,"nm":"Traçado"}],"ip":0,"op":130,"st":0,"bm":0}],"markers":[],"chars":[{"ch":"g","size":125,"style":"Regular","w":60.01,"data":{"shapes":[{"ty":"gr","it":[{"ind":0,"ty":"sh","ix":1,"ks":{"a":0,"k":{"i":[[0.846,1.677],[2.571,0],[1.139,-1.27],[0,-2.311],[0,0],[2.766,1.449],[3.776,0],[2.637,-1.123],[2.018,-2.213],[1.09,-3.223],[0,-4.004],[-1.791,-4.102],[-3.337,-2.278],[-4.46,0],[-2.686,1.498],[-2.051,2.865],[0.13,-1.969],[0.764,-1.726],[1.904,-0.961],[3.45,0],[1.302,0.309],[0.928,0.635],[0.764,0.895],[0.716,0.879],[1.953,0],[1.106,-1.025],[0,-1.628],[-1.953,-2.035],[-3.613,-1.286],[-4.59,0],[-3.369,1.009],[-2.084,2.083],[-0.945,3.19],[0,4.427],[0,0]],"o":[[-0.847,-1.676],[-1.791,0],[-1.14,1.27],[0,0],[-2.377,-3.092],[-2.767,-1.448],[-3.158,0],[-2.637,1.123],[-2.019,2.214],[-1.091,3.223],[0,5.371],[1.79,4.102],[3.336,2.279],[3.711,0],[2.686,-1.497],[-0.066,4.362],[-0.13,1.969],[-0.765,1.725],[-1.904,0.96],[-1.693,0],[-1.302,-0.31],[-0.928,-0.635],[-0.765,-0.896],[-1.465,-1.726],[-1.563,0],[-1.107,1.025],[0,2.148],[1.953,2.034],[3.613,1.286],[5.013,0],[3.369,-1.009],[2.083,-2.084],[0.944,-3.191],[0,0],[0,-3.157]],"v":[[54.639,-50.464],[49.512,-52.979],[45.117,-51.074],[43.408,-45.703],[43.408,-43.896],[35.693,-50.708],[25.879,-52.881],[17.188,-51.196],[10.205,-46.191],[5.542,-38.037],[3.906,-27.197],[6.592,-12.988],[14.282,-3.418],[25.977,0],[35.571,-2.246],[42.676,-8.789],[42.383,0.708],[41.04,6.25],[37.036,10.278],[29.004,11.719],[24.512,11.255],[21.167,9.839],[18.628,7.544],[16.406,4.883],[11.279,2.295],[7.275,3.833],[5.615,7.813],[8.545,14.087],[16.895,19.067],[29.199,20.996],[41.772,19.482],[49.951,14.844],[54.492,6.934],[55.908,-4.492],[55.908,-43.213]],"c":true},"ix":2},"nm":"g","mn":"ADBE Vector Shape - Group","hd":false},{"ind":1,"ty":"sh","ix":2,"ks":{"a":0,"k":{"i":[[-2.295,2.898],[-3.809,0],[-2.393,-3.027],[0,-5.436],[1.237,-2.393],[1.969,-1.188],[2.213,0],[2.36,2.767],[0,5.404]],"o":[[2.295,-2.897],[3.906,0],[2.393,3.027],[0,3.418],[-1.237,2.393],[-1.97,1.189],[-3.744,0],[-2.361,-2.766],[0,-5.338]],"v":[[20.728,-38.672],[29.883,-43.018],[39.331,-38.477],[42.92,-25.781],[41.064,-17.065],[36.255,-11.694],[29.98,-9.912],[20.825,-14.063],[17.285,-26.318]],"c":true},"ix":2},"nm":"g","mn":"ADBE Vector Shape - Group","hd":false}],"nm":"g","np":5,"cix":2,"bm":0,"ix":1,"mn":"ADBE Vector Group","hd":false}]},"fFamily":"Arial Rounded MT Bold"},{"ch":"l","size":125,"style":"Regular","w":27.1,"data":{"shapes":[{"ty":"gr","it":[{"ind":0,"ty":"sh","ix":1,"ks":{"a":0,"k":{"i":[[-1.221,-1.399],[-1.953,0],[-1.254,1.35],[0,2.702],[0,0],[1.237,1.351],[2.018,0],[1.188,-1.367],[0,-2.669],[0,0]],"o":[[1.221,1.399],[1.985,0],[1.253,-1.35],[0,0],[0,-2.702],[-1.237,-1.35],[-2.019,0],[-1.189,1.367],[0,0],[0,2.605]],"v":[[8.716,-0.879],[13.477,1.221],[18.335,-0.806],[20.215,-6.885],[20.215,-64.697],[18.359,-70.776],[13.477,-72.803],[8.667,-70.752],[6.885,-64.697],[6.885,-6.885]],"c":true},"ix":2},"nm":"l","mn":"ADBE Vector Shape - Group","hd":false}],"nm":"l","np":3,"cix":2,"bm":0,"ix":1,"mn":"ADBE Vector Group","hd":false}]},"fFamily":"Arial Rounded MT Bold"},{"ch":"o","size":125,"style":"Regular","w":60.4,"data":{"shapes":[{"ty":"gr","it":[{"ind":0,"ty":"sh","ix":1,"ks":{"a":0,"k":{"i":[[1.221,3.32],[2.344,2.409],[3.288,1.302],[4.036,0],[3.288,-1.286],[2.311,-2.376],[1.237,-3.352],[0,-4.036],[-1.221,-3.304],[-2.361,-2.425],[-3.223,-1.302],[-4.037,0],[-3.255,1.286],[-2.344,2.409],[-1.237,3.353],[0,3.972]],"o":[[-1.221,-3.32],[-2.344,-2.409],[-3.288,-1.302],[-3.972,0],[-3.288,1.286],[-2.312,2.377],[-1.237,3.353],[0,4.004],[1.221,3.304],[2.36,2.425],[3.223,1.302],[4.069,0],[3.255,-1.286],[2.344,-2.409],[1.237,-3.352],[0,-4.004]],"v":[[54.956,-36.865],[49.609,-45.459],[41.162,-51.025],[30.176,-52.979],[19.287,-51.05],[10.889,-45.557],[5.566,-36.963],[3.711,-25.879],[5.542,-14.917],[10.913,-6.323],[19.287,-0.732],[30.176,1.221],[41.162,-0.708],[49.561,-6.25],[54.932,-14.893],[56.787,-25.879]],"c":true},"ix":2},"nm":"o","mn":"ADBE Vector Shape - Group","hd":false},{"ind":1,"ty":"sh","ix":2,"ks":{"a":0,"k":{"i":[[2.393,-3.043],[4.036,0],[1.969,1.384],[1.057,2.605],[0,3.484],[-1.074,2.637],[-1.986,1.351],[-2.605,0],[-2.393,-3.027],[0,-5.436]],"o":[[-2.393,3.044],[-2.67,0],[-1.97,-1.383],[-1.058,-2.604],[0,-3.516],[1.074,-2.637],[1.985,-1.35],[4.036,0],[2.393,3.027],[0,5.371]],"v":[[39.819,-13.257],[30.176,-8.691],[23.218,-10.767],[18.677,-16.748],[17.09,-25.879],[18.701,-35.107],[23.291,-41.089],[30.176,-43.115],[39.819,-38.574],[43.408,-25.879]],"c":true},"ix":2},"nm":"o","mn":"ADBE Vector Shape - Group","hd":false}],"nm":"o","np":5,"cix":2,"bm":0,"ix":1,"mn":"ADBE Vector Group","hd":false}]},"fFamily":"Arial Rounded MT Bold"},{"ch":"b","size":125,"style":"Regular","w":61.18,"data":{"shapes":[{"ty":"gr","it":[{"ind":0,"ty":"sh","ix":1,"ks":{"a":0,"k":{"i":[[1.106,1.318],[2.051,0],[1.09,-1.383],[0,-2.702],[0,0],[-1.123,-1.286],[-1.888,0],[-1.205,1.286],[0,2.507],[0,0],[-0.896,-0.846],[-1.27,-0.797],[-1.807,-0.488],[-2.051,0],[-2.783,1.35],[-1.953,2.474],[-1.025,3.369],[0,4.037],[1.839,3.988],[3.336,2.1],[4.427,0],[2.604,-1.383],[2.506,-2.604],[0,0]],"o":[[-1.107,-1.318],[-1.953,0],[-1.091,1.384],[0,0],[0,2.507],[1.123,1.286],[1.855,0],[1.204,-1.286],[0,0],[1.465,1.693],[0.895,0.847],[1.27,0.798],[1.807,0.488],[3.352,0],[2.783,-1.35],[1.953,-2.473],[1.025,-3.369],[0,-5.469],[-1.839,-3.987],[-3.337,-2.1],[-3.841,0],[-2.605,1.384],[0,0],[0,-2.441]],"v":[[17.529,-70.825],[12.793,-72.803],[8.228,-70.728],[6.592,-64.6],[6.592,-6.396],[8.276,-0.708],[12.793,1.221],[17.383,-0.708],[19.189,-6.396],[19.189,-7.715],[22.729,-3.906],[25.977,-1.44],[30.591,0.488],[36.377,1.221],[45.581,-0.806],[52.686,-6.543],[57.153,-15.308],[58.691,-26.416],[55.933,-40.601],[48.169,-49.731],[36.523,-52.881],[26.855,-50.806],[19.189,-44.824],[19.189,-65.186]],"c":true},"ix":2},"nm":"b","mn":"ADBE Vector Shape - Group","hd":false},{"ind":1,"ty":"sh","ix":2,"ks":{"a":0,"k":{"i":[[-1.14,2.621],[-1.986,1.384],[-2.539,0],[-1.855,-1.383],[-1.009,-2.539],[0,-3.516],[2.425,-2.913],[3.352,0],[2.425,2.849],[0,5.306]],"o":[[1.139,-2.62],[1.985,-1.383],[2.473,0],[1.855,1.384],[1.009,2.539],[0,5.437],[-2.425,2.914],[-3.939,0],[-2.425,-2.848],[0,-3.613]],"v":[[21.533,-34.937],[26.221,-40.942],[33.008,-43.018],[39.502,-40.942],[43.799,-35.059],[45.313,-25.977],[41.675,-13.452],[33.008,-9.082],[23.462,-13.354],[19.824,-25.586]],"c":true},"ix":2},"nm":"b","mn":"ADBE Vector Shape - Group","hd":false}],"nm":"b","np":5,"cix":2,"bm":0,"ix":1,"mn":"ADBE Vector Group","hd":false}]},"fFamily":"Arial Rounded MT Bold"},{"ch":".","size":125,"style":"Regular","w":31.3,"data":{"shapes":[{"ty":"gr","it":[{"ind":0,"ty":"sh","ix":1,"ks":{"a":0,"k":{"i":[[-1.449,1.318],[0,2.312],[1.448,1.416],[2.051,0],[1.399,-1.432],[0,-1.985],[-1.465,-1.302],[-2.019,0]],"o":[[1.448,-1.318],[0,-2.018],[-1.449,-1.416],[-2.051,0],[-1.4,1.433],[0,2.344],[1.465,1.302],[1.953,0]],"v":[[20.825,-0.757],[22.998,-6.201],[20.825,-11.353],[15.576,-13.477],[10.4,-11.328],[8.301,-6.201],[10.498,-0.732],[15.723,1.221]],"c":true},"ix":2},"nm":".","mn":"ADBE Vector Shape - Group","hd":false}],"nm":".","np":3,"cix":2,"bm":0,"ix":1,"mn":"ADBE Vector Group","hd":false}]},"fFamily":"Arial Rounded MT Bold"},{"ch":"c","size":125,"style":"Regular","w":59.42,"data":{"shapes":[{"ty":"gr","it":[{"ind":0,"ty":"sh","ix":1,"ks":{"a":0,"k":{"i":[[1.074,1.237],[1.627,0],[0.944,-0.846],[0.813,-1.497],[1.904,-1.237],[2.669,0],[1.66,0.765],[1.172,1.482],[0.618,2.1],[0,2.507],[-2.409,3.076],[-3.939,0],[-1.775,-1.237],[-1.628,-2.473],[-0.732,-0.569],[-1.107,0],[-1.189,1.107],[0,1.595],[1.057,1.807],[2.002,1.595],[2.881,1.009],[3.45,0],[4.004,-2.295],[2.116,-4.199],[0,-5.469],[-4.623,-4.801],[-8.236,0],[-3.093,1.041],[-2.035,1.709],[-0.993,1.888],[0,1.66]],"o":[[-1.074,-1.237],[-1.367,0],[-0.945,0.847],[-1.465,2.539],[-1.904,1.237],[-1.986,0],[-1.66,-0.764],[-1.172,-1.481],[-0.619,-2.1],[0,-5.338],[2.409,-3.076],[2.734,0],[1.774,1.237],[0.911,1.27],[0.732,0.57],[1.692,0],[1.188,-1.106],[0,-1.563],[-1.058,-1.807],[-2.002,-1.595],[-2.881,-1.009],[-5.566,0],[-4.004,2.295],[-2.116,4.199],[0,8.073],[4.622,4.802],[3.873,0],[3.092,-1.041],[2.034,-1.709],[0.993,-1.888],[0,-1.399]],"v":[[53.076,-19.238],[49.023,-21.094],[45.557,-19.824],[42.92,-16.309],[37.866,-10.645],[31.006,-8.789],[25.537,-9.937],[21.289,-13.306],[18.604,-18.677],[17.676,-25.586],[21.289,-38.208],[30.811,-42.822],[37.573,-40.967],[42.676,-35.4],[45.142,-32.642],[47.9,-31.787],[52.222,-33.447],[54.004,-37.5],[52.417,-42.554],[47.827,-47.656],[40.503,-51.563],[31.006,-53.076],[16.65,-49.634],[7.471,-39.893],[4.297,-25.391],[11.23,-6.079],[30.518,1.123],[40.967,-0.439],[48.657,-4.565],[53.198,-9.961],[54.688,-15.283]],"c":true},"ix":2},"nm":"c","mn":"ADBE Vector Shape - Group","hd":false}],"nm":"c","np":3,"cix":2,"bm":0,"ix":1,"mn":"ADBE Vector Group","hd":false}]},"fFamily":"Arial Rounded MT Bold"},{"ch":"m","size":125,"style":"Regular","w":88.48,"data":{"shapes":[{"ty":"gr","it":[{"ind":0,"ty":"sh","ix":1,"ks":{"a":0,"k":{"i":[[-0.977,2.246],[-1.579,1.042],[-1.758,0],[-1.074,-1.172],[-0.244,-1.725],[0,-2.864],[0,0],[-1.286,-1.416],[-2.019,0],[-1.27,1.399],[0,2.8],[0,0],[1.139,2.409],[2.637,1.433],[3.645,0],[2.571,-1.318],[2.246,-2.734],[2.409,1.335],[3.352,0],[2.637,-1.302],[2.311,-2.766],[0,0],[1.221,1.221],[1.823,0],[1.155,-1.302],[0,-2.506],[0,0],[-1.286,-1.416],[-2.019,0],[-1.254,1.416],[0,2.767],[0,0],[-1.384,2.995],[-4.362,0],[-1.009,-1.188],[-0.228,-1.855],[0,-3.352],[0,0],[-1.254,-1.399],[-2.019,0],[-1.27,1.399],[0,2.8],[0,0]],"o":[[0.879,-1.758],[1.579,-1.041],[2.18,0],[1.074,1.172],[0.244,1.726],[0,0],[0,2.767],[1.286,1.416],[2.083,0],[1.27,-1.399],[0,0],[0,-5.176],[-1.302,-2.669],[-2.637,-1.432],[-3.125,0],[-2.572,1.318],[-1.563,-2.702],[-2.409,-1.334],[-3.223,0],[-2.637,1.302],[0,0],[0,-2.148],[-1.221,-1.221],[-1.888,0],[-1.156,1.302],[0,0],[0,2.767],[1.286,1.416],[2.051,0],[1.253,-1.416],[0,0],[0,-5.598],[1.383,-2.995],[2.18,0],[1.009,1.189],[0.227,1.855],[0,0],[0,2.8],[1.253,1.399],[2.083,0],[1.27,-1.399],[0,0],[0,-5.696]],"v":[[52.686,-36.816],[56.372,-41.016],[61.377,-42.578],[66.26,-40.82],[68.237,-36.475],[68.604,-29.59],[68.604,-7.178],[70.532,-0.903],[75.488,1.221],[80.518,-0.879],[82.422,-7.178],[82.422,-33.203],[80.713,-44.58],[74.805,-50.732],[65.381,-52.881],[56.836,-50.903],[49.609,-44.824],[43.652,-50.879],[35.01,-52.881],[26.221,-50.928],[18.799,-44.824],[18.799,-46.094],[16.968,-51.147],[12.402,-52.979],[7.837,-51.025],[6.104,-45.313],[6.104,-7.178],[8.032,-0.903],[12.988,1.221],[17.944,-0.903],[19.824,-7.178],[19.824,-25.195],[21.899,-38.086],[30.518,-42.578],[35.303,-40.796],[37.158,-36.23],[37.5,-28.418],[37.5,-7.178],[39.38,-0.879],[44.287,1.221],[49.316,-0.879],[51.221,-7.178],[51.221,-24.902]],"c":true},"ix":2},"nm":"m","mn":"ADBE Vector Shape - Group","hd":false}],"nm":"m","np":3,"cix":2,"bm":0,"ix":1,"mn":"ADBE Vector Group","hd":false}]},"fFamily":"Arial Rounded MT Bold"},{"ch":"c","size":60,"style":"Regular","w":38.5,"data":{"shapes":[{"ty":"gr","it":[{"ind":0,"ty":"sh","ix":1,"ks":{"a":0,"k":{"i":[[-5.267,0],[-2.767,3],[0,5.467],[0,0],[0,0],[0,0],[3.666,0],[0,4.267],[0,0],[-3.667,0],[0,-4.333],[0,0],[0,0],[0,0],[2.766,3],[5.266,0],[2.766,-3],[0,-5.466],[0,0],[-2.767,-3]],"o":[[5.266,0],[2.766,-3],[0,0],[0,0],[0,0],[0,4.267],[-3.667,0],[0,0],[0,-4.333],[3.666,0],[0,0],[0,0],[0,0],[0,-5.466],[-2.767,-3],[-5.267,0],[-2.767,3],[0,0],[0,5.467],[2.766,3]],"v":[[19.6,1],[31.65,-3.5],[35.8,-16.2],[35.8,-26.1],[25.4,-26.1],[25.4,-15.4],[19.9,-9],[14.4,-15.4],[14.4,-54.5],[19.9,-61],[25.4,-54.5],[25.4,-46.4],[35.8,-46.4],[35.8,-53.8],[31.65,-66.5],[19.6,-71],[7.55,-66.5],[3.4,-53.8],[3.4,-16.2],[7.55,-3.5]],"c":true},"ix":2},"nm":"c","mn":"ADBE Vector Shape - Group","hd":false}],"nm":"c","np":3,"cix":2,"bm":0,"ix":1,"mn":"ADBE Vector Group","hd":false}]},"fFamily":"Bebas Neue"},{"ch":"o","size":60,"style":"Regular","w":40,"data":{"shapes":[{"ty":"gr","it":[{"ind":0,"ty":"sh","ix":1,"ks":{"a":0,"k":{"i":[[-5.4,0],[-2.867,3.067],[0,5.6],[0,0],[2.866,3.067],[5.4,0],[2.866,-3.066],[0,-5.6],[0,0],[-2.867,-3.066]],"o":[[5.4,0],[2.866,-3.066],[0,0],[0,-5.6],[-2.867,-3.066],[-5.4,0],[-2.867,3.067],[0,0],[0,5.6],[2.866,3.067]],"v":[[20,1],[32.4,-3.6],[36.7,-16.6],[36.7,-53.4],[32.4,-66.4],[20,-71],[7.6,-66.4],[3.3,-53.4],[3.3,-16.6],[7.6,-3.6]],"c":true},"ix":2},"nm":"o","mn":"ADBE Vector Shape - Group","hd":false},{"ind":1,"ty":"sh","ix":2,"ks":{"a":0,"k":{"i":[[3.8,0],[0,4.6],[0,0],[-3.8,0],[0,-4.6],[0,0]],"o":[[-3.8,0],[0,0],[0,-4.6],[3.8,0],[0,0],[0,4.6]],"v":[[20,-9],[14.3,-15.9],[14.3,-54.1],[20,-61],[25.7,-54.1],[25.7,-15.9]],"c":true},"ix":2},"nm":"o","mn":"ADBE Vector Shape - Group","hd":false}],"nm":"o","np":5,"cix":2,"bm":0,"ix":1,"mn":"ADBE Vector Group","hd":false}]},"fFamily":"Bebas Neue"},{"ch":"m","size":60,"style":"Regular","w":53.8,"data":{"shapes":[{"ty":"gr","it":[{"ind":0,"ty":"sh","ix":1,"ks":{"a":0,"k":{"i":[[0,0],[0,0],[0,0],[0,0],[0,0],[0,0],[0,0],[0,0],[0,0],[0,0],[0,0],[0,0],[0,0],[0,0],[0,0],[0,0]],"o":[[0,0],[0,0],[0,0],[0,0],[0,0],[0,0],[0,0],[0,0],[0,0],[0,0],[0,0],[0,0],[0,0],[0,0],[0,0],[0,0]],"v":[[4.1,0],[13.7,0],[13.7,-53],[13.9,-53],[21.9,0],[31.1,0],[39.1,-53],[39.3,-53],[39.3,0],[49.7,0],[49.7,-70],[34,-70],[27,-19.9],[26.8,-19.9],[19.8,-70],[4.1,-70]],"c":true},"ix":2},"nm":"m","mn":"ADBE Vector Shape - Group","hd":false}],"nm":"m","np":3,"cix":2,"bm":0,"ix":1,"mn":"ADBE Vector Group","hd":false}]},"fFamily":"Bebas Neue"},{"ch":"f","size":150,"style":"Regular","w":34.4,"data":{"shapes":[{"ty":"gr","it":[{"ind":0,"ty":"sh","ix":1,"ks":{"a":0,"k":{"i":[[0,0],[0,0],[0,0],[0,0],[0,0],[0,0],[0,0],[0,0],[0,0],[0,0]],"o":[[0,0],[0,0],[0,0],[0,0],[0,0],[0,0],[0,0],[0,0],[0,0],[0,0]],"v":[[4.1,0],[15.1,0],[15.1,-30.5],[29.3,-30.5],[29.3,-40.5],[15.1,-40.5],[15.1,-60],[33.2,-60],[33.2,-70],[4.1,-70]],"c":true},"ix":2},"nm":"f","mn":"ADBE Vector Shape - Group","hd":false}],"nm":"f","np":3,"cix":2,"bm":0,"ix":1,"mn":"ADBE Vector Group","hd":false}]},"fFamily":"Bebas Neue"},{"ch":"i","size":150,"style":"Regular","w":19.2,"data":{"shapes":[{"ty":"gr","it":[{"ind":0,"ty":"sh","ix":1,"ks":{"a":0,"k":{"i":[[0,0],[0,0],[0,0],[0,0]],"o":[[0,0],[0,0],[0,0],[0,0]],"v":[[4.1,0],[15.1,0],[15.1,-70],[4.1,-70]],"c":true},"ix":2},"nm":"i","mn":"ADBE Vector Shape - Group","hd":false}],"nm":"i","np":3,"cix":2,"bm":0,"ix":1,"mn":"ADBE Vector Group","hd":false}]},"fFamily":"Bebas Neue"},{"ch":"q","size":150,"style":"Regular","w":40,"data":{"shapes":[{"ty":"gr","it":[{"ind":0,"ty":"sh","ix":1,"ks":{"a":0,"k":{"i":[[-5,0],[0,0],[0,0],[0,0],[0.6,0.2],[0.4,0.667],[0,4.667],[0,0],[2.866,3.067],[5.4,0],[2.866,-3.066],[0,-5.6],[0,0],[-2.867,-3.066],[-5.4,0],[-2.067,0.8]],"o":[[0,0],[0,0],[0,0],[-1.134,0],[-0.6,-0.2],[2.066,-3],[0,0],[0,-5.6],[-2.867,-3.066],[-5.4,0],[-2.867,3.067],[0,0],[0,5.6],[2.866,3.067],[2.8,0],[1.133,4.466]],"v":[[36.5,6.5],[39.4,6.5],[39.4,-3.5],[37.7,-3.5],[35.1,-3.8],[33.6,-5.1],[36.7,-16.6],[36.7,-53.4],[32.4,-66.4],[20,-71],[7.6,-66.4],[3.3,-53.4],[3.3,-16.6],[7.6,-3.6],[20,1],[27.3,-0.2]],"c":true},"ix":2},"nm":"q","mn":"ADBE Vector Shape - Group","hd":false},{"ind":1,"ty":"sh","ix":2,"ks":{"a":0,"k":{"i":[[3.8,0],[0,4.6],[0,0],[-3.8,0],[0,-4.6],[0,0]],"o":[[-3.8,0],[0,0],[0,-4.6],[3.8,0],[0,0],[0,4.6]],"v":[[20,-9],[14.3,-15.9],[14.3,-54.1],[20,-61],[25.7,-54.1],[25.7,-15.9]],"c":true},"ix":2},"nm":"q","mn":"ADBE Vector Shape - Group","hd":false}],"nm":"q","np":5,"cix":2,"bm":0,"ix":1,"mn":"ADBE Vector Group","hd":false}]},"fFamily":"Bebas Neue"},{"ch":"u","size":150,"style":"Regular","w":40.2,"data":{"shapes":[{"ty":"gr","it":[{"ind":0,"ty":"sh","ix":1,"ks":{"a":0,"k":{"i":[[-5.334,0],[-2.8,3.034],[0,5.667],[0,0],[0,0],[0,0],[0.966,-1.066],[1.8,0],[0.966,1.067],[0,2.4],[0,0],[0,0],[0,0],[-2.8,-3.033]],"o":[[5.333,0],[2.8,-3.033],[0,0],[0,0],[0,0],[0,2.4],[-0.967,1.067],[-1.8,0],[-0.967,-1.066],[0,0],[0,0],[0,0],[0,5.667],[2.8,3.034]],"v":[[20.1,1],[32.3,-3.55],[36.5,-16.6],[36.5,-70],[25.9,-70],[25.9,-15.8],[24.45,-10.6],[20.3,-9],[16.15,-10.6],[14.7,-15.8],[14.7,-70],[3.7,-70],[3.7,-16.6],[7.9,-3.55]],"c":true},"ix":2},"nm":"u","mn":"ADBE Vector Shape - Group","hd":false}],"nm":"u","np":3,"cix":2,"bm":0,"ix":1,"mn":"ADBE Vector Group","hd":false}]},"fFamily":"Bebas Neue"},{"ch":"e","size":150,"style":"Regular","w":36.3,"data":{"shapes":[{"ty":"gr","it":[{"ind":0,"ty":"sh","ix":1,"ks":{"a":0,"k":{"i":[[0,0],[0,0],[0,0],[0,0],[0,0],[0,0],[0,0],[0,0],[0,0],[0,0],[0,0],[0,0]],"o":[[0,0],[0,0],[0,0],[0,0],[0,0],[0,0],[0,0],[0,0],[0,0],[0,0],[0,0],[0,0]],"v":[[4.1,0],[34.1,0],[34.1,-10],[15.1,-10],[15.1,-31.5],[30.2,-31.5],[30.2,-41.5],[15.1,-41.5],[15.1,-60],[34.1,-60],[34.1,-70],[4.1,-70]],"c":true},"ix":2},"nm":"e","mn":"ADBE Vector Shape - Group","hd":false}],"nm":"e","np":3,"cix":2,"bm":0,"ix":1,"mn":"ADBE Vector Group","hd":false}]},"fFamily":"Bebas Neue"},{"ch":" ","size":150,"style":"Regular","w":16,"data":{},"fFamily":"Bebas Neue"},{"ch":"a","size":150,"style":"Regular","w":40.6,"data":{"shapes":[{"ty":"gr","it":[{"ind":0,"ty":"sh","ix":1,"ks":{"a":0,"k":{"i":[[0,0],[0,0],[0,0],[0,0],[0,0],[0,0],[0,0],[0,0],[0,0]],"o":[[0,0],[0,0],[0,0],[0,0],[0,0],[0,0],[0,0],[0,0],[0,0]],"v":[[1.2,0],[11.4,0],[13.4,-13.7],[25.9,-13.7],[25.9,-13.9],[27.9,0],[38.9,0],[27.5,-70],[12.6,-70]],"c":true},"ix":2},"nm":"a","mn":"ADBE Vector Shape - Group","hd":false},{"ind":1,"ty":"sh","ix":2,"ks":{"a":0,"k":{"i":[[0,0],[0,0],[0,0],[0,0]],"o":[[0,0],[0,0],[0,0],[0,0]],"v":[[14.7,-23.2],[19.5,-57.8],[19.7,-57.8],[24.6,-23.2]],"c":true},"ix":2},"nm":"a","mn":"ADBE Vector Shape - Group","hd":false}],"nm":"a","np":5,"cix":2,"bm":0,"ix":1,"mn":"ADBE Vector Group","hd":false}]},"fFamily":"Bebas Neue"},{"ch":"s","size":150,"style":"Regular","w":37.2,"data":{"shapes":[{"ty":"gr","it":[{"ind":0,"ty":"sh","ix":1,"ks":{"a":0,"k":{"i":[[-5.334,0],[-2.834,3.067],[0,5.734],[1.733,3.267],[4.6,4],[1.366,2.2],[0,2.534],[-3.667,0],[-0.934,-1.1],[0,-2.4],[0,0],[0,0],[0,0],[2.7,3.034],[5.266,0],[2.8,-3.033],[0,-5.533],[-1.8,-3.233],[-4.534,-4],[-1.334,-2.233],[0,-2.933],[0.966,-1.1],[1.866,0],[0,4.534],[0,0],[0,0],[0,0],[-2.734,-3.033]],"o":[[5.4,0],[2.833,-3.066],[0,-4.4],[-1.734,-3.266],[-3.6,-3.133],[-1.367,-2.2],[0,-4.466],[1.8,0],[0.933,1.1],[0,0],[0,0],[0,0],[0,-5.666],[-2.7,-3.033],[-5.334,0],[-2.8,3.034],[0,4.067],[1.8,3.234],[3.6,3.134],[1.333,2.234],[0,2.467],[-0.967,1.1],[-3.8,0],[0,0],[0,0],[0,0],[0,5.667],[2.733,3.034]],"v":[[18.4,1],[30.75,-3.6],[35,-16.8],[32.4,-28.3],[22.9,-39.2],[15.45,-47.2],[13.4,-54.3],[18.9,-61],[23,-59.35],[24.4,-54.1],[24.4,-50.5],[34.8,-50.5],[34.8,-53.4],[30.75,-66.45],[18.8,-71],[6.6,-66.45],[2.4,-53.6],[5.1,-42.65],[14.6,-31.8],[22,-23.75],[24,-16],[22.55,-10.65],[18.3,-9],[12.6,-15.8],[12.6,-20.6],[2.2,-20.6],[2.2,-16.6],[6.3,-3.55]],"c":true},"ix":2},"nm":"s","mn":"ADBE Vector Shape - Group","hd":false}],"nm":"s","np":3,"cix":2,"bm":0,"ix":1,"mn":"ADBE Vector Group","hd":false}]},"fFamily":"Bebas Neue"}]}